setup.py
lpo/__init__.py
lpo/arith.py
lpo/config.py
lpo/counter.py
lpo/expression.py
lpo/expressionset.py
lpo/proofs.py
lpo/rule.py
lpo/symbol.py
lpo/tables.py
lpo.egg-info/PKG-INFO
lpo.egg-info/SOURCES.txt
lpo.egg-info/dependency_links.txt
lpo.egg-info/entry_points.txt
lpo.egg-info/not-zip-safe
lpo.egg-info/requires.txt
lpo.egg-info/top_level.txt
lpo/test/__init__.py
lpo/test/alltests.py
lpo/test/doctests.py
lpo/test/testbase.py
lpo/test/testexpression.py
lpo/test/testexpressionset.py
lpo/test/testsymbol.py
