Metadata-Version: 1.0
Name: lpo
Version: 0.1.2
Summary: Finite domain first order logic system
Home-page: http://pypi.python.org/pypi/lpo
Author: Enrique Perez Arnaud
Author-email: enriquepablo@gmail.com
License: GPL
Keywords: logic programming prolog
Platform: UNKNOWN
